pomotracker/__init__.py
pomotracker/database.py
pomotracker/main.py
pomotracker/notification.py
pomotracker/session.py
pomotracker/window.py
pomotracker-0.1.0.dist-info/METADATA
pomotracker-0.1.0.dist-info/WHEEL
pomotracker-0.1.0.dist-info/entry_points.txt
pomotracker-0.1.0.dist-info/RECORD
