Metadata-Version: 2.4
Name: pomotracker
Version: 0.1.0
Summary: A Pomodoro tracker with a special 'borrow time' feature.
License: MIT
Requires-Python: >=3.12
Requires-Dist: prompt-toolkit>=3.0.43
Requires-Dist: psutil>=5.9.8
